imohash/__init__.py
imohash/imohash.py
imohash/imohash_test.py
imohash-1.1.0.dist-info/LICENSE
imohash-1.1.0.dist-info/METADATA
imohash-1.1.0.dist-info/WHEEL
imohash-1.1.0.dist-info/entry_points.txt
imohash-1.1.0.dist-info/top_level.txt
imohash-1.1.0.dist-info/RECORD
