Metadata-Version: 2.1
Name: imohash
Version: 1.1.0
Summary: Fast hashing for large files
Author-email: Jim Kalafut <jim@kalafut.net>
License: MIT
Project-URL: Homepage, https://github.com/kalafut/py-imohash
Keywords: hash,hashing,imohash
Classifier: Development Status :: 5 - Production/Stable
Classifier: Intended Audience :: Developers
Classifier: Topic :: Software Development
Classifier: Topic :: Software Development :: Libraries :: Python Modules
Classifier: Topic :: Utilities
Classifier: License :: OSI Approved :: MIT License
Classifier: Programming Language :: Python :: 3
Classifier: Programming Language :: Python :: 3.3
Classifier: Programming Language :: Python :: 3.4
Classifier: Programming Language :: Python :: 3.5
Classifier: Programming Language :: Python :: 3.6
Classifier: Programming Language :: Python :: 3.11
License-File: LICENSE
Requires-Dist: mmh3>=2.5.1
Requires-Dist: varint>=1.0.2
